LICENSE
ansible_aisnippet/__init__.py
ansible_aisnippet/aisnippet.py
ansible_aisnippet/helpers.py
ansible_aisnippet/main.py
ansible_aisnippet/snippets.json
ansible_aisnippet-0.1.2.dist-info/LICENSE
ansible_aisnippet-0.1.2.dist-info/METADATA
ansible_aisnippet-0.1.2.dist-info/WHEEL
ansible_aisnippet-0.1.2.dist-info/entry_points.txt
ansible_aisnippet-0.1.2.dist-info/RECORD
