Metadata-Version: 2.1
Name: ansible-aisnippet
Version: 0.1.2
Summary: Ansible-aisnippet Generate ansible tasks with ChatGPT.
Home-page: https://blog.stephane-robert.info/
Keywords: ansible,module,ChatGPT
Author: Stephane ROBERT
Author-email: robert.stephane.28@gmail.com
Requires-Python: >=3.10,<4.0
Classifier: Programming Language :: Python :: 3
Classifier: Programming Language :: Python :: 3.10
Classifier: Programming Language :: Python :: 3.11
Requires-Dist: Jinja2 (>=3.1.2,<4.0.0)
Requires-Dist: gensim (>=4.3.1,<5.0.0)
Requires-Dist: importlib-metadata (>=4.12.0,<5.0.0)
Requires-Dist: jieba (>=0.42.1,<0.43.0)
Requires-Dist: openai (>=0.27.2,<0.28.0)
Requires-Dist: rich (>=12.6.0,<13.0.0)
Requires-Dist: ruamel.yaml (>=0.17.21,<0.18.0)
Requires-Dist: typer[all] (>=0.6.1,<0.7.0)
Project-URL: Repository, https://github.com/stephrobert/ansible-aisnippet
